CHANGELOG.txt
LICENCE.txt
MANIFEST.in
README.txt
setup.py
test.py
andycalculator/__init__.py
andycalculator.egg-info/PKG-INFO
andycalculator.egg-info/SOURCES.txt
andycalculator.egg-info/dependency_links.txt
andycalculator.egg-info/top_level.txt