Metadata-Version: 2.1
Name: andycalculator
Version: 0.0.2
Summary: A very basic calculator
Home-page: UNKNOWN
Author: Joshua Lowe
Author-email: anandyadav0110@gmail.com
License: MIT
Keywords: calculator
Platform: UNKNOWN
Classifier: Development Status :: 5 - Production/Stable
Classifier: Intended Audience :: Education
Classifier: Operating System :: Microsoft :: Windows :: Windows 10
Classifier: License :: OSI Approved :: MIT License
Classifier: Programming Language :: Python :: 3
License-File: LICENCE.txt
